instapost/__init__.py
instapost/client.py
instapost/exceptions.py
instapost/api/__init__.py
instapost/api/base.py
instapost/media/__init__.py
instapost/media/uploader.py
instapost/posting/__init__.py
instapost/posting/carousel.py
instapost/posting/image.py
instapost/posting/reel.py
instapost-0.2.0.dist-info/METADATA
instapost-0.2.0.dist-info/WHEEL
instapost-0.2.0.dist-info/licenses/LICENSE
instapost-0.2.0.dist-info/RECORD
