Metadata-Version: 2.4
Name: instapost
Version: 0.2.0
Summary: A Python library for automating Instagram posting (images, reels, carousels)
Project-URL: Homepage, https://blaya.ia.br
Project-URL: Repository, https://github.com/pedroluz/instapost
Project-URL: Documentation, https://github.com/pedroluz/instapost#readme
Project-URL: Issues, https://github.com/pedroluz/instapost/issues
Author-email: Pedro Luz <blaya.luz@gmail.com>
Maintainer-email: Pedro Luz <blaya.luz@gmail.com>
License: MIT
License-File: LICENSE
Keywords: automation,carousel,graph-api,instagram,meta,reels,social-media
Classifier: Development Status :: 4 - Beta
Classifier: Environment :: Web Environment
Classifier: Intended Audience :: Developers
Classifier: License :: OSI Approved :: MIT License
Classifier: Natural Language :: English
Classifier: Operating System :: OS Independent
Classifier: Programming Language :: Python
Classifier: Programming Language :: Python :: 3
Classifier: Programming Language :: Python :: 3.10
Classifier: Programming Language :: Python :: 3.11
Classifier: Programming Language :: Python :: 3.12
Classifier: Programming Language :: Python :: 3.13
Classifier: Programming Language :: Python :: 3.14
Classifier: Topic :: Internet :: WWW/HTTP
Classifier: Topic :: Multimedia :: Graphics
Classifier: Topic :: Office/Business
Classifier: Typing :: Typed
Requires-Python: >=3.10
Requires-Dist: requests>=2.28.0
Provides-Extra: dev
Requires-Dist: pytest-cov>=4.0; extra == 'dev'
Requires-Dist: pytest>=7.0; extra == 'dev'
